pypysh-0.1.0.dist-info/METADATA
pypysh-0.1.0.dist-info/WHEEL
pypysh-0.1.0.dist-info/entry_points.txt
pypysh/__init__.pyi
pypysh/__init__.py
pypysh/__main__.py
pypysh/pypysh.abi3.so
pypysh-0.1.0.dist-info/RECORD
